MANIFEST.in
README.txt
setup.cfg
setup.py
bahai/__init__.py
bahai.theme.egg-info/PKG-INFO
bahai.theme.egg-info/SOURCES.txt
bahai.theme.egg-info/dependency_links.txt
bahai.theme.egg-info/entry_points.txt
bahai.theme.egg-info/namespace_packages.txt
bahai.theme.egg-info/not-zip-safe
bahai.theme.egg-info/paster_plugins.txt
bahai.theme.egg-info/requires.txt
bahai.theme.egg-info/top_level.txt
bahai/theme/__init__.py
bahai/theme/configure.zcml
bahai/theme/profiles.zcml
bahai/theme/setuphandlers.py
bahai/theme/skins.zcml
bahai/theme/tests.py
bahai/theme/version.txt
bahai/theme/browser/__init__.py
bahai/theme/browser/configure.zcml
bahai/theme/browser/interfaces.py
bahai/theme/browser/viewlet.pt
bahai/theme/browser/viewlets.py
bahai/theme/browser/images/README.txt
bahai/theme/browser/stylesheets/README.txt
bahai/theme/browser/stylesheets/main.css
bahai/theme/locales/README.txt
bahai/theme/profiles/default/bahai.theme_various.txt
bahai/theme/profiles/default/cssregistry.xml
bahai/theme/profiles/default/jsregistry.xml
bahai/theme/profiles/default/metadata.xml
bahai/theme/profiles/default/propertiestool.xml
bahai/theme/profiles/default/skins.xml
bahai/theme/profiles/default/viewlets.xml
bahai/theme/skins/bahai_theme_custom_images/000event.jpg
bahai/theme/skins/bahai_theme_custom_images/000forlop.jpg
bahai/theme/skins/bahai_theme_custom_images/000forlopv.jpg
bahai/theme/skins/bahai_theme_custom_images/000forlopvII.jpg
bahai/theme/skins/bahai_theme_custom_images/000forlopvII.png
bahai/theme/skins/bahai_theme_custom_images/000globalnav_shadows.gif
bahai/theme/skins/bahai_theme_custom_images/000head30.gif
bahai/theme/skins/bahai_theme_custom_images/000head30.jpg
bahai/theme/skins/bahai_theme_custom_images/000head30.png
bahai/theme/skins/bahai_theme_custom_images/000lique.png
bahai/theme/skins/bahai_theme_custom_images/000liqueII.png
bahai/theme/skins/bahai_theme_custom_images/000mail.jpg
bahai/theme/skins/bahai_theme_custom_images/000mail_icon.jpg
bahai/theme/skins/bahai_theme_custom_images/000menuanddevider.png
bahai/theme/skins/bahai_theme_custom_images/000menuanddeviderII.png
bahai/theme/skins/bahai_theme_custom_images/000newsitemicon.jpg
bahai/theme/skins/bahai_theme_custom_images/000print.jpg
bahai/theme/skins/bahai_theme_custom_images/000topconf.jpg
