Metadata-Version: 1.0
Name: bahai.theme
Version: 1.0.3
Summary: Theme for Bahai.dk site
Home-page: http://svn.plone.org/svn/collective/
Author: UNKNOWN
Author-email: UNKNOWN
License: GPL
Platform: UNKNOWN
Classifier: Framework :: Plone
Classifier: Programming Language :: Python
